{"name":"Betrayal","maxBlock":10,"BPM":133,"offset":500,"notes":[{"LPB":16,"num":320,"block":7,"type":1,"renge":2,"notes":[]},{"LPB":16,"num":336,"block":7,"type":1,"renge":2,"notes":[]},{"LPB":16,"num":352,"block":7,"type":1,"renge":2,"notes":[]},{"LPB":16,"num":368,"block":7,"type":1,"renge":2,"notes":[]},{"LPB":16,"num":384,"block":0,"type":1,"renge":2,"notes":[]},{"LPB":16,"num":400,"block":0,"type":1,"renge":2,"notes":[]},{"LPB":16,"num":416,"block":0,"type":1,"renge":2,"notes":[]},{"LPB":16,"num":432,"block":0,"type":1,"renge":2,"notes":[]},{"LPB":16,"num":448,"block":7,"type":2,"renge":2,"notes":[{"LPB":16,"num":464,"block":7,"type":2,"renge":2,"notes":[]}]},{"LPB":16,"num":480,"block":0,"type":2,"renge":2,"notes":[{"LPB":16,"num":496,"block":0,"type":2,"renge":2,"notes":[]}]},{"LPB":16,"num":512,"block":0,"type":2,"renge":9,"notes":[{"LPB":16,"num":575,"block":0,"type":2,"renge":9,"notes":[]}]},{"LPB":16,"num":640,"block":0,"type":0,"renge":2,"notes":[]},{"LPB":16,"num":656,"block":0,"type":0,"renge":2,"notes":[]},{"LPB":16,"num":672,"block":7,"type":0,"renge":2,"notes":[]},{"LPB":16,"num":688,"block":7,"type":0,"renge":2,"notes":[]},{"LPB":16,"num":704,"block":0,"type":0,"renge":2,"notes":[]},{"LPB":16,"num":720,"block":0,"type":0,"renge":2,"notes":[]},{"LPB":16,"num":736,"block":7,"type":0,"renge":2,"notes":[]},{"LPB":16,"num":752,"block":7,"type":0,"renge":2,"notes":[]},{"LPB":16,"num":768,"block":0,"type":0,"renge":2,"notes":[]},{"LPB":16,"num":784,"block":0,"type":0,"renge":2,"notes":[]},{"LPB":16,"num":800,"block":7,"type":0,"renge":2,"notes":[]},{"LPB":16,"num":816,"block":7,"type":0,"renge":2,"notes":[]},{"LPB":16,"num":832,"block":0,"type":0,"renge":2,"notes":[]},{"LPB":16,"num":848,"block":0,"type":0,"renge":2,"notes":[]},{"LPB":16,"num":864,"block":7,"type":0,"renge":2,"notes":[]},{"LPB":16,"num":880,"block":7,"type":0,"renge":2,"notes":[]},{"LPB":16,"num":896,"block":0,"type":2,"renge":3,"notes":[{"LPB":16,"num":912,"block":0,"type":2,"renge":3,"notes":[]}]},{"LPB":16,"num":928,"block":6,"type":2,"renge":3,"notes":[{"LPB":16,"num":944,"block":6,"type":2,"renge":3,"notes":[]}]},{"LPB":16,"num":960,"block":0,"type":2,"renge":3,"notes":[{"LPB":16,"num":976,"block":0,"type":2,"renge":3,"notes":[]}]},{"LPB":16,"num":992,"block":6,"type":2,"renge":3,"notes":[{"LPB":16,"num":1008,"block":6,"type":2,"renge":3,"notes":[]}]},{"LPB":16,"num":1024,"block":0,"type":2,"renge":3,"notes":[{"LPB":16,"num":1040,"block":0,"type":2,"renge":3,"notes":[]}]},{"LPB":16,"num":1056,"block":6,"type":2,"renge":3,"notes":[{"LPB":16,"num":1072,"block":6,"type":2,"renge":3,"notes":[]}]},{"LPB":16,"num":1088,"block":0,"type":2,"renge":3,"notes":[{"LPB":16,"num":1104,"block":3,"type":2,"renge":1,"notes":[]}]},{"LPB":16,"num":1120,"block":6,"type":2,"renge":3,"notes":[{"LPB":16,"num":1136,"block":6,"type":2,"renge":1,"notes":[]}]},{"LPB":16,"num":1152,"block":0,"type":0,"renge":2,"notes":[]},{"LPB":16,"num":1168,"block":7,"type":0,"renge":2,"notes":[]},{"LPB":16,"num":1184,"block":0,"type":0,"renge":2,"notes":[]},{"LPB":16,"num":1200,"block":7,"type":0,"renge":2,"notes":[]},{"LPB":16,"num":1280,"block":0,"type":0,"renge":3,"notes":[]},{"LPB":16,"num":1280,"block":6,"type":0,"renge":3,"notes":[]},{"LPB":16,"num":1296,"block":6,"type":0,"renge":3,"notes":[]},{"LPB":16,"num":1296,"block":0,"type":0,"renge":3,"notes":[]},{"LPB":16,"num":1312,"block":6,"type":0,"renge":3,"notes":[]},{"LPB":16,"num":1312,"block":0,"type":0,"renge":3,"notes":[]},{"LPB":16,"num":1328,"block":6,"type":0,"renge":3,"notes":[]},{"LPB":16,"num":1328,"block":0,"type":0,"renge":3,"notes":[]},{"LPB":16,"num":1344,"block":6,"type":0,"renge":3,"notes":[]},{"LPB":16,"num":1344,"block":0,"type":0,"renge":3,"notes":[]},{"LPB":16,"num":1360,"block":7,"type":0,"renge":2,"notes":[]},{"LPB":16,"num":1376,"block":0,"type":0,"renge":2,"notes":[]},{"LPB":16,"num":1392,"block":7,"type":0,"renge":2,"notes":[]},{"LPB":16,"num":1408,"block":0,"type":0,"renge":2,"notes":[]},{"LPB":16,"num":1424,"block":8,"type":1,"renge":1,"notes":[]},{"LPB":16,"num":1440,"block":0,"type":1,"renge":1,"notes":[]},{"LPB":16,"num":1456,"block":8,"type":1,"renge":1,"notes":[]},{"LPB":16,"num":1472,"block":0,"type":1,"renge":1,"notes":[]},{"LPB":16,"num":1488,"block":8,"type":1,"renge":1,"notes":[]},{"LPB":16,"num":1504,"block":0,"type":1,"renge":1,"notes":[]},{"LPB":16,"num":1520,"block":8,"type":1,"renge":1,"notes":[]},{"LPB":16,"num":1536,"block":0,"type":1,"renge":1,"notes":[]},{"LPB":16,"num":1552,"block":6,"type":0,"renge":3,"notes":[]},{"LPB":16,"num":1568,"block":0,"type":2,"renge":2,"notes":[{"LPB":16,"num":1584,"block":0,"type":2,"renge":2,"notes":[]}]},{"LPB":16,"num":1600,"block":0,"type":0,"renge":3,"notes":[]},{"LPB":16,"num":1616,"block":7,"type":2,"renge":2,"notes":[{"LPB":16,"num":1632,"block":7,"type":2,"renge":2,"notes":[]}]},{"LPB":16,"num":1648,"block":6,"type":0,"renge":3,"notes":[]},{"LPB":16,"num":1664,"block":2,"type":2,"renge":3,"notes":[{"LPB":16,"num":1680,"block":0,"type":2,"renge":1,"notes":[]}]},{"LPB":16,"num":1696,"block":0,"type":0,"renge":3,"notes":[]},{"LPB":16,"num":1712,"block":5,"type":2,"renge":2,"notes":[{"LPB":16,"num":1728,"block":8,"type":2,"renge":1,"notes":[]}]},{"LPB":16,"num":1744,"block":0,"type":2,"renge":1,"notes":[{"LPB":16,"num":1760,"block":0,"type":2,"renge":1,"notes":[]}]},{"LPB":16,"num":1760,"block":7,"type":2,"renge":2,"notes":[{"LPB":16,"num":1776,"block":7,"type":2,"renge":2,"notes":[]}]},{"LPB":16,"num":1776,"block":0,"type":2,"renge":3,"notes":[{"LPB":16,"num":1792,"block":0,"type":2,"renge":3,"notes":[]}]},{"LPB":16,"num":1816,"block":5,"type":2,"renge":3,"notes":[{"LPB":16,"num":1856,"block":5,"type":2,"renge":3,"notes":[]}]},{"LPB":16,"num":1840,"block":0,"type":2,"renge":3,"notes":[{"LPB":16,"num":1856,"block":0,"type":2,"renge":3,"notes":[]}]},{"LPB":16,"num":1872,"block":6,"type":0,"renge":3,"notes":[]},{"LPB":16,"num":1888,"block":0,"type":0,"renge":3,"notes":[]},{"LPB":16,"num":1904,"block":6,"type":0,"renge":3,"notes":[]},{"LPB":16,"num":1920,"block":0,"type":0,"renge":3,"notes":[]},{"LPB":16,"num":1936,"block":6,"type":0,"renge":3,"notes":[]},{"LPB":16,"num":1952,"block":0,"type":0,"renge":3,"notes":[]},{"LPB":16,"num":1968,"block":6,"type":0,"renge":3,"notes":[]},{"LPB":16,"num":1984,"block":0,"type":2,"renge":2,"notes":[{"LPB":16,"num":2016,"block":0,"type":2,"renge":2,"notes":[]}]},{"LPB":16,"num":2016,"block":8,"type":2,"renge":1,"notes":[{"LPB":16,"num":2048,"block":8,"type":2,"renge":1,"notes":[]}]},{"LPB":16,"num":2048,"block":0,"type":2,"renge":2,"notes":[{"LPB":16,"num":2080,"block":0,"type":2,"renge":2,"notes":[]}]},{"LPB":16,"num":2080,"block":6,"type":2,"renge":4,"notes":[{"LPB":16,"num":2112,"block":6,"type":2,"renge":4,"notes":[]}]},{"LPB":16,"num":2112,"block":0,"type":2,"renge":3,"notes":[{"LPB":16,"num":2144,"block":0,"type":2,"renge":3,"notes":[]}]},{"LPB":16,"num":2128,"block":6,"type":0,"renge":2,"notes":[]},{"LPB":16,"num":2144,"block":6,"type":0,"renge":2,"notes":[]},{"LPB":16,"num":2160,"block":6,"type":2,"renge":3,"notes":[{"LPB":16,"num":2192,"block":6,"type":2,"renge":3,"notes":[]}]},{"LPB":16,"num":2176,"block":0,"type":0,"renge":2,"notes":[]},{"LPB":16,"num":2192,"block":0,"type":0,"renge":2,"notes":[]},{"LPB":16,"num":2208,"block":0,"type":2,"renge":3,"notes":[{"LPB":16,"num":2240,"block":0,"type":2,"renge":3,"notes":[]}]},{"LPB":16,"num":2224,"block":6,"type":0,"renge":2,"notes":[]},{"LPB":16,"num":2240,"block":6,"type":0,"renge":2,"notes":[]},{"LPB":16,"num":2256,"block":6,"type":2,"renge":3,"notes":[{"LPB":16,"num":2288,"block":6,"type":2,"renge":3,"notes":[]}]},{"LPB":16,"num":2272,"block":0,"type":0,"renge":2,"notes":[]},{"LPB":16,"num":2288,"block":0,"type":0,"renge":2,"notes":[]},{"LPB":16,"num":2304,"block":0,"type":2,"renge":5,"notes":[{"LPB":16,"num":2360,"block":0,"type":2,"renge":1,"notes":[]}]},{"LPB":16,"num":2336,"block":6,"type":2,"renge":3,"notes":[{"LPB":16,"num":2360,"block":8,"type":2,"renge":1,"notes":[]}]},{"LPB":16,"num":2432,"block":7,"type":2,"renge":2,"notes":[{"LPB":16,"num":2448,"block":7,"type":2,"renge":2,"notes":[]}]},{"LPB":16,"num":2440,"block":0,"type":1,"renge":3,"notes":[]},{"LPB":16,"num":2464,"block":0,"type":2,"renge":2,"notes":[{"LPB":16,"num":2480,"block":0,"type":2,"renge":2,"notes":[]}]},{"LPB":16,"num":2472,"block":6,"type":1,"renge":3,"notes":[]},{"LPB":16,"num":2496,"block":0,"type":2,"renge":2,"notes":[{"LPB":16,"num":2512,"block":0,"type":2,"renge":2,"notes":[]}]},{"LPB":16,"num":2504,"block":6,"type":1,"renge":3,"notes":[]},{"LPB":16,"num":2528,"block":7,"type":2,"renge":2,"notes":[{"LPB":16,"num":2544,"block":7,"type":2,"renge":2,"notes":[]}]},{"LPB":16,"num":2536,"block":0,"type":1,"renge":3,"notes":[]},{"LPB":16,"num":2560,"block":0,"type":2,"renge":3,"notes":[{"LPB":16,"num":2592,"block":0,"type":2,"renge":3,"notes":[]}]},{"LPB":16,"num":2568,"block":7,"type":1,"renge":2,"notes":[]},{"LPB":16,"num":2576,"block":5,"type":1,"renge":3,"notes":[]},{"LPB":16,"num":2584,"block":7,"type":1,"renge":2,"notes":[]},{"LPB":16,"num":2608,"block":5,"type":2,"renge":4,"notes":[{"LPB":16,"num":2640,"block":5,"type":2,"renge":4,"notes":[]}]},{"LPB":16,"num":2616,"block":0,"type":1,"renge":2,"notes":[]},{"LPB":16,"num":2624,"block":1,"type":1,"renge":3,"notes":[]},{"LPB":16,"num":2632,"block":0,"type":1,"renge":2,"notes":[]},{"LPB":16,"num":2656,"block":0,"type":1,"renge":3,"notes":[]},{"LPB":16,"num":2664,"block":6,"type":1,"renge":3,"notes":[]},{"LPB":16,"num":2672,"block":0,"type":1,"renge":3,"notes":[]},{"LPB":16,"num":2680,"block":6,"type":1,"renge":3,"notes":[]},{"LPB":16,"num":2688,"block":0,"type":0,"renge":4,"notes":[]},{"LPB":16,"num":2704,"block":5,"type":0,"renge":4,"notes":[]},{"LPB":16,"num":2720,"block":0,"type":0,"renge":4,"notes":[]},{"LPB":16,"num":2736,"block":5,"type":0,"renge":4,"notes":[]},{"LPB":16,"num":2752,"block":0,"type":0,"renge":4,"notes":[]},{"LPB":16,"num":2768,"block":5,"type":0,"renge":4,"notes":[]},{"LPB":16,"num":2784,"block":0,"type":0,"renge":4,"notes":[]},{"LPB":16,"num":2800,"block":5,"type":0,"renge":4,"notes":[]},{"LPB":16,"num":2816,"block":0,"type":0,"renge":4,"notes":[]},{"LPB":16,"num":2816,"block":7,"type":2,"renge":2,"notes":[{"LPB":16,"num":2832,"block":7,"type":2,"renge":2,"notes":[]}]},{"LPB":16,"num":2832,"block":0,"type":0,"renge":4,"notes":[]},{"LPB":16,"num":2848,"block":5,"type":0,"renge":4,"notes":[]},{"LPB":16,"num":2848,"block":0,"type":2,"renge":2,"notes":[{"LPB":16,"num":2864,"block":0,"type":2,"renge":2,"notes":[]}]},{"LPB":16,"num":2864,"block":5,"type":0,"renge":4,"notes":[]},{"LPB":16,"num":2880,"block":0,"type":0,"renge":4,"notes":[]},{"LPB":16,"num":2880,"block":5,"type":0,"renge":4,"notes":[]},{"LPB":16,"num":2896,"block":0,"type":0,"renge":4,"notes":[]},{"LPB":16,"num":2896,"block":5,"type":0,"renge":4,"notes":[]},{"LPB":16,"num":2912,"block":5,"type":0,"renge":4,"notes":[]},{"LPB":16,"num":2912,"block":0,"type":0,"renge":4,"notes":[]},{"LPB":16,"num":2928,"block":6,"type":0,"renge":3,"notes":[]},{"LPB":16,"num":2928,"block":0,"type":0,"renge":3,"notes":[]},{"LPB":16,"num":2944,"block":0,"type":2,"renge":3,"notes":[{"LPB":16,"num":3072,"block":0,"type":2,"renge":2,"notes":[]}]},{"LPB":16,"num":2944,"block":6,"type":2,"renge":3,"notes":[{"LPB":16,"num":3008,"block":6,"type":2,"renge":3,"notes":[]}]},{"LPB":16,"num":3072,"block":6,"type":2,"renge":3,"notes":[{"LPB":16,"num":3136,"block":7,"type":2,"renge":2,"notes":[]}]},{"LPB":16,"num":3136,"block":0,"type":2,"renge":2,"notes":[{"LPB":16,"num":3200,"block":0,"type":2,"renge":1,"notes":[]}]},{"LPB":16,"num":3200,"block":7,"type":2,"renge":2,"notes":[{"LPB":16,"num":3328,"block":8,"type":2,"renge":1,"notes":[]}]},{"LPB":16,"num":3216,"block":0,"type":0,"renge":2,"notes":[]},{"LPB":16,"num":3232,"block":3,"type":0,"renge":2,"notes":[]},{"LPB":16,"num":3248,"block":0,"type":0,"renge":2,"notes":[]},{"LPB":16,"num":3264,"block":3,"type":0,"renge":2,"notes":[]},{"LPB":16,"num":3280,"block":0,"type":0,"renge":2,"notes":[]},{"LPB":16,"num":3296,"block":3,"type":0,"renge":2,"notes":[]},{"LPB":16,"num":3312,"block":0,"type":0,"renge":2,"notes":[]},{"LPB":16,"num":3328,"block":3,"type":0,"renge":2,"notes":[]},{"LPB":16,"num":3344,"block":7,"type":0,"renge":2,"notes":[]},{"LPB":16,"num":3360,"block":0,"type":0,"renge":2,"notes":[]},{"LPB":16,"num":3376,"block":8,"type":0,"renge":1,"notes":[]},{"LPB":17,"num":3604,"block":0,"type":2,"renge":1,"notes":[{"LPB":17,"num":3670,"block":0,"type":2,"renge":1,"notes":[]},{"LPB":17,"num":3672,"block":0,"type":2,"renge":9,"notes":[]}]},{"LPB":16,"num":3392,"block":8,"type":2,"renge":1,"notes":[{"LPB":16,"num":3454,"block":8,"type":2,"renge":1,"notes":[]},{"LPB":16,"num":3456,"block":0,"type":2,"renge":9,"notes":[]}]},{"LPB":16,"num":3472,"block":0,"type":2,"renge":1,"notes":[{"LPB":16,"num":3488,"block":0,"type":2,"renge":1,"notes":[]}]},{"LPB":16,"num":3480,"block":7,"type":1,"renge":2,"notes":[]},{"LPB":16,"num":3496,"block":7,"type":2,"renge":2,"notes":[{"LPB":16,"num":3511,"block":7,"type":2,"renge":2,"notes":[]}]},{"LPB":16,"num":3504,"block":0,"type":1,"renge":2,"notes":[]},{"LPB":16,"num":3520,"block":0,"type":2,"renge":3,"notes":[{"LPB":16,"num":3536,"block":0,"type":2,"renge":3,"notes":[]}]},{"LPB":16,"num":3528,"block":6,"type":1,"renge":3,"notes":[]},{"LPB":16,"num":3544,"block":6,"type":2,"renge":3,"notes":[{"LPB":16,"num":3560,"block":6,"type":2,"renge":3,"notes":[]}]},{"LPB":16,"num":3552,"block":0,"type":1,"renge":4,"notes":[]},{"LPB":16,"num":3568,"block":0,"type":2,"renge":4,"notes":[{"LPB":16,"num":3584,"block":0,"type":2,"renge":4,"notes":[]}]},{"LPB":16,"num":3576,"block":5,"type":1,"renge":4,"notes":[]},{"LPB":16,"num":3592,"block":6,"type":2,"renge":3,"notes":[{"LPB":16,"num":3608,"block":7,"type":2,"renge":2,"notes":[]}]},{"LPB":16,"num":3600,"block":0,"type":1,"renge":3,"notes":[]},{"LPB":16,"num":3616,"block":0,"type":2,"renge":2,"notes":[{"LPB":16,"num":3632,"block":0,"type":2,"renge":1,"notes":[]}]},{"LPB":16,"num":3624,"block":7,"type":1,"renge":2,"notes":[]},{"LPB":16,"num":3640,"block":7,"type":2,"renge":1,"notes":[{"LPB":16,"num":3656,"block":8,"type":2,"renge":1,"notes":[]}]},{"LPB":16,"num":3648,"block":0,"type":1,"renge":1,"notes":[]},{"LPB":16,"num":3664,"block":1,"type":2,"renge":1,"notes":[{"LPB":16,"num":3680,"block":0,"type":2,"renge":1,"notes":[]}]},{"LPB":16,"num":3672,"block":8,"type":1,"renge":1,"notes":[]},{"LPB":16,"num":3712,"block":0,"type":2,"renge":5,"notes":[{"LPB":16,"num":3768,"block":0,"type":2,"renge":1,"notes":[]}]},{"LPB":16,"num":3728,"block":7,"type":0,"renge":2,"notes":[]},{"LPB":16,"num":3744,"block":7,"type":0,"renge":2,"notes":[]},{"LPB":16,"num":3760,"block":7,"type":0,"renge":2,"notes":[]},{"LPB":16,"num":3776,"block":5,"type":2,"renge":4,"notes":[{"LPB":16,"num":3832,"block":8,"type":2,"renge":1,"notes":[]}]},{"LPB":16,"num":3792,"block":0,"type":0,"renge":2,"notes":[]},{"LPB":16,"num":3808,"block":0,"type":0,"renge":2,"notes":[]},{"LPB":16,"num":3824,"block":0,"type":0,"renge":2,"notes":[]},{"LPB":16,"num":3840,"block":0,"type":2,"renge":1,"notes":[{"LPB":16,"num":3896,"block":0,"type":2,"renge":3,"notes":[]}]},{"LPB":16,"num":3856,"block":8,"type":0,"renge":1,"notes":[]},{"LPB":16,"num":3872,"block":7,"type":0,"renge":1,"notes":[]},{"LPB":16,"num":3888,"block":7,"type":0,"renge":2,"notes":[]},{"LPB":16,"num":3904,"block":8,"type":2,"renge":1,"notes":[{"LPB":16,"num":3960,"block":6,"type":2,"renge":3,"notes":[]}]},{"LPB":16,"num":3920,"block":0,"type":0,"renge":2,"notes":[]},{"LPB":16,"num":3936,"block":1,"type":0,"renge":2,"notes":[]},{"LPB":16,"num":3952,"block":0,"type":0,"renge":3,"notes":[]},{"LPB":16,"num":4000,"block":8,"type":0,"renge":1,"notes":[]},{"LPB":16,"num":4016,"block":7,"type":2,"renge":1,"notes":[{"LPB":16,"num":4024,"block":7,"type":2,"renge":1,"notes":[]}]},{"LPB":16,"num":4032,"block":0,"type":0,"renge":2,"notes":[]},{"LPB":16,"num":4048,"block":0,"type":0,"renge":2,"notes":[]},{"LPB":16,"num":4072,"block":0,"type":2,"renge":2,"notes":[{"LPB":16,"num":4088,"block":0,"type":2,"renge":2,"notes":[]}]},{"LPB":16,"num":4080,"block":6,"type":0,"renge":3,"notes":[]},{"LPB":16,"num":4096,"block":6,"type":0,"renge":3,"notes":[]},{"LPB":16,"num":4104,"block":8,"type":2,"renge":1,"notes":[{"LPB":16,"num":4112,"block":8,"type":2,"renge":1,"notes":[]}]},{"LPB":16,"num":4128,"block":0,"type":0,"renge":1,"notes":[]},{"LPB":16,"num":4144,"block":0,"type":2,"renge":2,"notes":[{"LPB":16,"num":4152,"block":0,"type":2,"renge":1,"notes":[]}]},{"LPB":16,"num":4160,"block":7,"type":0,"renge":2,"notes":[]},{"LPB":16,"num":4176,"block":7,"type":0,"renge":2,"notes":[]},{"LPB":16,"num":4184,"block":0,"type":2,"renge":3,"notes":[{"LPB":16,"num":4192,"block":0,"type":2,"renge":3,"notes":[]}]},{"LPB":16,"num":4200,"block":7,"type":2,"renge":2,"notes":[{"LPB":16,"num":4208,"block":8,"type":2,"renge":1,"notes":[]}]},{"LPB":16,"num":4224,"block":0,"type":2,"renge":2,"notes":[{"LPB":16,"num":4252,"block":0,"type":2,"renge":1,"notes":[]},{"LPB":16,"num":4256,"block":0,"type":2,"renge":4,"notes":[]}]},{"LPB":16,"num":4240,"block":7,"type":1,"renge":1,"notes":[]},{"LPB":16,"num":4272,"block":0,"type":0,"renge":3,"notes":[]},{"LPB":16,"num":4288,"block":6,"type":0,"renge":3,"notes":[]},{"LPB":16,"num":4304,"block":0,"type":0,"renge":3,"notes":[]},{"LPB":16,"num":4320,"block":6,"type":0,"renge":3,"notes":[]},{"LPB":16,"num":4336,"block":0,"type":0,"renge":3,"notes":[]},{"LPB":16,"num":4352,"block":7,"type":0,"renge":3,"notes":[]},{"LPB":16,"num":4368,"block":0,"type":2,"renge":4,"notes":[{"LPB":16,"num":4384,"block":0,"type":2,"renge":4,"notes":[]}]},{"LPB":16,"num":4376,"block":8,"type":0,"renge":1,"notes":[]},{"LPB":16,"num":4400,"block":6,"type":2,"renge":3,"notes":[{"LPB":16,"num":4416,"block":6,"type":2,"renge":3,"notes":[]}]},{"LPB":16,"num":4408,"block":0,"type":0,"renge":1,"notes":[]},{"LPB":16,"num":4432,"block":6,"type":2,"renge":3,"notes":[{"LPB":16,"num":4448,"block":7,"type":2,"renge":2,"notes":[]}]},{"LPB":16,"num":4440,"block":1,"type":0,"renge":2,"notes":[]},{"LPB":16,"num":4464,"block":0,"type":2,"renge":3,"notes":[{"LPB":16,"num":4480,"block":0,"type":2,"renge":2,"notes":[]}]},{"LPB":16,"num":4472,"block":6,"type":0,"renge":2,"notes":[]},{"LPB":16,"num":4496,"block":0,"type":2,"renge":5,"notes":[{"LPB":16,"num":4512,"block":1,"type":2,"renge":1,"notes":[]}]},{"LPB":16,"num":4504,"block":6,"type":0,"renge":3,"notes":[]}]}